judy/__init__.py
judy/api/__init__.py
judy/cache/__init__.py
judy/cache/cache.py
judy/cli/__init__.py
judy/cli/install.py
judy/cli/manager.py
judy/cli/pipeline.py
judy/cli/run.py
judy/config/__init__.py
judy/config/data_models.py
judy/config/files/example_dataset_config.yaml
judy/config/files/example_eval_config.yaml
judy/config/files/example_run_config.yaml
judy/config/logging.py
judy/config/settings.py
judy/config/validator.py
judy/dataset/__init__.py
judy/dataset/base.py
judy/dataset/data_models.py
judy/dataset/formatters.py
judy/dataset/loader.py
judy/evaluation/__init__.py
judy/evaluation/evaluator.py
judy/evaluation/prompt_builder.py
judy/evaluation/prompts.py
judy/responders/__init__.py
judy/responders/base_responder.py
judy/responders/data_models.py
judy/responders/disinfo_reiteration_responder.py
judy/responders/disinfo_wedging_responder.py
judy/responders/mt_q_responder.py
judy/responders/mt_qac_responder.py
judy/responders/st_q_responder.py
judy/responders/st_qa_responder.py
judy/responders/st_qac_responder.py
judy/responders/st_qam_responder.py
judy/responders/summ_responder.py
judy/utils/__init__.py
judy/utils/llm.py
judy/utils/request_retry.py
judy/utils/utils.py
judy/web_app/__init__.py
judy/web_app/breadcrumb.py
judy/web_app/config.py
judy/web_app/main.py
judy/web_app/static/styles.css
judy/web_app/templates/about_page.html
judy/web_app/templates/base.html
judy/web_app/templates/card_page.html
judy/web_app/templates/heatmap_macro.html
judy/web_app/templates/info_card.html
judy/web_app/templates/model_page.html
judy/web_app/templates/raw_results.html
judy/web_app/templates/run_dashboard.html
judy/web_app/templates/run_page.html
judy/web_app/templates/table_macro.html
judy/web_app/utils.py
judy/web_app/views.py
judyeval-2.1.0.dist-info/LICENSE
judyeval-2.1.0.dist-info/METADATA
judyeval-2.1.0.dist-info/WHEEL
judyeval-2.1.0.dist-info/entry_points.txt
judyeval-2.1.0.dist-info/RECORD
