Metadata-Version: 2.1
Name: judyeval
Version: 2.1.0
Summary: Judy is a python library and framework to evaluate the text-generation capabilities of Large Language Models (LLM) using a Judge LLM.
Author: Linden Hutchinson
Author-email: linden.hutchinson@tesserent.com
Requires-Python: >=3.10,<4.0
Classifier: Programming Language :: Python :: 3
Classifier: Programming Language :: Python :: 3.10
Classifier: Programming Language :: Python :: 3.11
Classifier: Programming Language :: Python :: 3.12
Requires-Dist: black (>=23.10.1,<24.0.0)
Requires-Dist: click (>=8.1.7,<9.0.0)
Requires-Dist: datasets (>=2.14.5,<3.0.0)
Requires-Dist: easyllm (>=0.5.0,<0.6.0)
Requires-Dist: flask (>=3.0.0,<4.0.0)
Requires-Dist: numpy (==1.24.4)
Requires-Dist: openai (>=1.3.7,<2.0.0)
Requires-Dist: platformdirs (>=3.11.0,<4.0.0)
Requires-Dist: pytest (>=7.4.2,<8.0.0)
Requires-Dist: python-dotenv (>=1.0.0,<2.0.0)
Requires-Dist: sqlitedict (>=2.1.0,<3.0.0)
